[{
  "_id": {
    "$oid": "6631e6d98c7444839df0af03"
  },
  "idRoom": 24129946,
  "lastUpdate": {
    "$numberLong": "1715756874176"
  },
  "site": "CFPV",
  "date": {
    "$date": "2024-06-05T00:00:00.000Z"
  },
  "name": "Vennes - A02",
  "configSite": {
    "breakline": 0.1667,
    "tpiTime": 1,
    "firstTpiStart": 8,
    "numSlots": 8
  },
  "tpiDatas": [
    {
      "refTpi": 1893,
      "id": "cfpv_0_0",
      "candidat": "Emilien Charpié",
      "expert1": {
        "name": "Oberson Bernard",
        "offres": {
          "_id": {
            "$oid": "66445f65d04cad996abc7c4a"
          },
          "submit": []
        }
      },
      "expert2": {
        "name": "Wyssa Michael",
        "offres": {
          "_id": {
            "$oid": "66445f65d04cad996abc7c4b"
          },
          "submit": []
        }
      },
      "boss": {
        "name": "Jonathan Melly",
        "offres": {
          "_id": {
            "$oid": "66445f65d04cad996abc7c4c"
          },
          "submit": []
        }
      },
      "_id": {
        "$oid": "6631e6f48c7444839df0afcf"
      }
    },
    {
      "refTpi": 1962,
      "id": "cfpv_0_1",
      "candidat": "Mathis Broquet",
      "expert1": {
        "name": "Malherbe Roger",
        "offres": {
          "_id": {
            "$oid": "66445f65d04cad996abc7c4e"
          },
          "submit": []
        }
      },
      "expert2": {
        "name": "Mottier André",
        "offres": {
          "_id": {
            "$oid": "66445f65d04cad996abc7c4f"
          },
          "submit": []
        }
      },
      "boss": {
        "name": "Dimitrios Lymberis",
        "offres": {
          "_id": {
            "$oid": "66445f65d04cad996abc7c50"
          },
          "submit": []
        }
      },
      "_id": {
        "$oid": "6631e6f48c7444839df0afd1"
      }
    },
    {
      "refTpi": null,
      "id": "cfpv_0_2",
      "candidat": "",
      "expert1": {
        "name": "",
        "offres": {
          "_id": {
            "$oid": "66445f65d04cad996abc7c52"
          },
          "submit": []
        }
      },
      "expert2": {
        "name": "",
        "offres": {
          "_id": {
            "$oid": "66445f65d04cad996abc7c53"
          },
          "submit": []
        }
      },
      "boss": {
        "name": "",
        "offres": {
          "_id": {
            "$oid": "66445f65d04cad996abc7c54"
          },
          "submit": []
        }
      },
      "_id": {
        "$oid": "6634a2c252692c062bdd104f"
      }
    },
    {
      "refTpi": null,
      "id": "cfpv_0_3",
      "candidat": "",
      "expert1": {
        "name": "",
        "offres": {
          "_id": {
            "$oid": "66445f65d04cad996abc7c56"
          },
          "submit": []
        }
      },
      "expert2": {
        "name": "",
        "offres": {
          "_id": {
            "$oid": "66445f65d04cad996abc7c57"
          },
          "submit": []
        }
      },
      "boss": {
        "name": "",
        "offres": {
          "_id": {
            "$oid": "66445f65d04cad996abc7c58"
          },
          "submit": []
        }
      },
      "_id": {
        "$oid": "6634a2c252692c062bdd104b"
      }
    },
    {
      "refTpi": null,
      "id": "cfpv_0_4",
      "candidat": "",
      "expert1": {
        "name": "",
        "offres": {
          "_id": {
            "$oid": "66445f65d04cad996abc7c5a"
          },
          "submit": []
        }
      },
      "expert2": {
        "name": "",
        "offres": {
          "_id": {
            "$oid": "66445f65d04cad996abc7c5b"
          },
          "submit": []
        }
      },
      "boss": {
        "name": "",
        "offres": {
          "_id": {
            "$oid": "66445f65d04cad996abc7c5c"
          },
          "submit": []
        }
      },
      "_id": {
        "$oid": "6631e6f48c7444839df0afd2"
      }
    },
    {
      "refTpi": null,
      "id": "cfpv_0_5",
      "candidat": "",
      "expert1": {
        "name": "",
        "offres": {
          "_id": {
            "$oid": "66445f65d04cad996abc7c5e"
          },
          "submit": []
        }
      },
      "expert2": {
        "name": "",
        "offres": {
          "_id": {
            "$oid": "66445f65d04cad996abc7c5f"
          },
          "submit": []
        }
      },
      "boss": {
        "name": "",
        "offres": {
          "_id": {
            "$oid": "66445f65d04cad996abc7c60"
          },
          "submit": []
        }
      },
      "_id": {
        "$oid": "6631e6f48c7444839df0afd4"
      }
    },
    {
      "refTpi": null,
      "id": "cfpv_0_6",
      "candidat": "",
      "expert1": {
        "name": "",
        "offres": {
          "_id": {
            "$oid": "66445f65d04cad996abc7c62"
          },
          "submit": []
        }
      },
      "expert2": {
        "name": "",
        "offres": {
          "_id": {
            "$oid": "66445f65d04cad996abc7c63"
          },
          "submit": []
        }
      },
      "boss": {
        "name": "",
        "offres": {
          "_id": {
            "$oid": "66445f65d04cad996abc7c64"
          },
          "submit": []
        }
      },
      "_id": {
        "$oid": "6631e6f48c7444839df0afd8"
      }
    },
    {
      "refTpi": null,
      "id": "cfpv_0_7",
      "candidat": "",
      "expert1": {
        "name": "",
        "offres": {
          "_id": {
            "$oid": "66445f65d04cad996abc7c66"
          },
          "submit": []
        }
      },
      "expert2": {
        "name": "",
        "offres": {
          "_id": {
            "$oid": "66445f65d04cad996abc7c67"
          },
          "submit": []
        }
      },
      "boss": {
        "name": "",
        "offres": {
          "_id": {
            "$oid": "66445f65d04cad996abc7c68"
          },
          "submit": []
        }
      },
      "_id": {
        "$oid": "6631e6f48c7444839df0afdc"
      }
    }
  ],
  "__v": 0
},
{
  "_id": {
    "$oid": "6634a15252692c062bdd004a"
  },
  "idRoom": 24308705,
  "lastUpdate": {
    "$numberLong": "1715756874176"
  },
  "site": "CFPV",
  "date": {
    "$date": "2024-06-06T00:00:00.000Z"
  },
  "name": "Vennes - A02",
  "configSite": {
    "breakline": 0.1667,
    "tpiTime": 1,
    "firstTpiStart": 8,
    "numSlots": 8
  },
  "tpiDatas": [
    {
      "refTpi": 1952,
      "id": "cfpv_1_0",
      "candidat": "Samuel King Alexandre",
      "expert1": {
        "name": "Glassey Nicolas",
        "offres": {
          "_id": {
            "$oid": "66445f65d04cad996abc7c6c"
          },
          "submit": []
        }
      },
      "expert2": {
        "name": "Borboën Nicolas",
        "offres": {
          "_id": {
            "$oid": "66445f65d04cad996abc7c6d"
          },
          "submit": []
        }
      },
      "boss": {
        "name": "Aurélie Curchod",
        "offres": {
          "_id": {
            "$oid": "66445f65d04cad996abc7c6e"
          },
          "submit": []
        }
      },
      "_id": {
        "$oid": "6631e6f48c7444839df0afea"
      }
    },
    {
      "refTpi": 1929,
      "id": "cfpv_1_1",
      "candidat": "Tim Froidevaux",
      "expert1": {
        "name": "Graf Alexandre",
        "offres": {
          "_id": {
            "$oid": "66445f65d04cad996abc7c70"
          },
          "submit": []
        }
      },
      "expert2": {
        "name": "Sartoni Arnaud",
        "offres": {
          "_id": {
            "$oid": "66445f65d04cad996abc7c71"
          },
          "submit": []
        }
      },
      "boss": {
        "name": "Michel Delgado",
        "offres": {
          "_id": {
            "$oid": "66445f65d04cad996abc7c72"
          },
          "submit": []
        }
      },
      "_id": {
        "$oid": "6631e6f48c7444839df0afd0"
      }
    },
    {
      "refTpi": 1957,
      "id": "cfpv_1_2",
      "candidat": "Aurélien Dévaud",
      "expert1": {
        "name": "Montemayor Ernesto",
        "offres": {
          "_id": {
            "$oid": "66445f65d04cad996abc7c74"
          },
          "submit": []
        }
      },
      "expert2": {
        "name": "Viret Loic",
        "offres": {
          "_id": {
            "$oid": "66445f65d04cad996abc7c75"
          },
          "submit": []
        }
      },
      "boss": {
        "name": "Dimitrios Lymberis",
        "offres": {
          "_id": {
            "$oid": "66445f65d04cad996abc7c76"
          },
          "submit": []
        }
      },
      "_id": {
        "$oid": "6631e6f48c7444839df0afd3"
      }
    },
    {
      "refTpi": null,
      "id": "cfpv_1_3",
      "candidat": "",
      "expert1": {
        "name": "",
        "offres": {
          "_id": {
            "$oid": "66445f65d04cad996abc7c78"
          },
          "submit": []
        }
      },
      "expert2": {
        "name": "",
        "offres": {
          "_id": {
            "$oid": "66445f65d04cad996abc7c79"
          },
          "submit": []
        }
      },
      "boss": {
        "name": "",
        "offres": {
          "_id": {
            "$oid": "66445f65d04cad996abc7c7a"
          },
          "submit": []
        }
      },
      "_id": {
        "$oid": "6634a2c252692c062bdd1053"
      }
    },
    {
      "refTpi": null,
      "id": "cfpv_1_4",
      "candidat": "",
      "expert1": {
        "name": "",
        "offres": {
          "_id": {
            "$oid": "66445f65d04cad996abc7c7c"
          },
          "submit": []
        }
      },
      "expert2": {
        "name": "",
        "offres": {
          "_id": {
            "$oid": "66445f65d04cad996abc7c7d"
          },
          "submit": []
        }
      },
      "boss": {
        "name": "",
        "offres": {
          "_id": {
            "$oid": "66445f65d04cad996abc7c7e"
          },
          "submit": []
        }
      },
      "_id": {
        "$oid": "6634a2c252692c062bdd1057"
      }
    },
    {
      "refTpi": null,
      "id": "cfpv_1_5",
      "candidat": "",
      "expert1": {
        "name": "",
        "offres": {
          "_id": {
            "$oid": "66445f65d04cad996abc7c80"
          },
          "submit": []
        }
      },
      "expert2": {
        "name": "",
        "offres": {
          "_id": {
            "$oid": "66445f65d04cad996abc7c81"
          },
          "submit": []
        }
      },
      "boss": {
        "name": "",
        "offres": {
          "_id": {
            "$oid": "66445f65d04cad996abc7c82"
          },
          "submit": []
        }
      },
      "_id": {
        "$oid": "6634a2c252692c062bdd105b"
      }
    },
    {
      "refTpi": null,
      "id": "cfpv_1_6",
      "candidat": "",
      "expert1": {
        "name": "",
        "offres": {
          "_id": {
            "$oid": "66445f65d04cad996abc7c84"
          },
          "submit": []
        }
      },
      "expert2": {
        "name": "",
        "offres": {
          "_id": {
            "$oid": "66445f65d04cad996abc7c85"
          },
          "submit": []
        }
      },
      "boss": {
        "name": "",
        "offres": {
          "_id": {
            "$oid": "66445f65d04cad996abc7c86"
          },
          "submit": []
        }
      },
      "_id": {
        "$oid": "6634a2c252692c062bdd105f"
      }
    },
    {
      "refTpi": null,
      "id": "cfpv_1_7",
      "candidat": "",
      "expert1": {
        "name": "",
        "offres": {
          "_id": {
            "$oid": "66445f65d04cad996abc7c88"
          },
          "submit": []
        }
      },
      "expert2": {
        "name": "",
        "offres": {
          "_id": {
            "$oid": "66445f65d04cad996abc7c89"
          },
          "submit": []
        }
      },
      "boss": {
        "name": "",
        "offres": {
          "_id": {
            "$oid": "66445f65d04cad996abc7c8a"
          },
          "submit": []
        }
      },
      "_id": {
        "$oid": "6634a2c252692c062bdd1063"
      }
    }
  ],
  "__v": 0
},
{
  "_id": {
    "$oid": "6631e6d98c7444839df0af3b"
  },
  "idRoom": 24129968,
  "lastUpdate": {
    "$numberLong": "1715756874176"
  },
  "site": "CFPV",
  "date": {
    "$date": "2024-06-12T00:00:00.000Z"
  },
  "name": "Vennes - A11",
  "configSite": {
    "breakline": 0.1667,
    "tpiTime": 1,
    "firstTpiStart": 8,
    "numSlots": 8
  },
  "tpiDatas": [
    {
      "refTpi": 1976,
      "id": "cfpv_2_0",
      "candidat": "Mbayo Gregory",
      "expert1": {
        "name": "Borboën Nicolas",
        "offres": {
          "_id": {
            "$oid": "66445f65d04cad996abc7c8e"
          },
          "submit": []
        }
      },
      "expert2": {
        "name": "Oberson Bernard",
        "offres": {
          "_id": {
            "$oid": "66445f65d04cad996abc7c8f"
          },
          "submit": []
        }
      },
      "boss": {
        "name": "Alain Girardet",
        "offres": {
          "_id": {
            "$oid": "66445f65d04cad996abc7c90"
          },
          "submit": []
        }
      },
      "_id": {
        "$oid": "6631ea298c7444839df0b402"
      }
    },
    {
      "refTpi": 1887,
      "id": "cfpv_2_1",
      "candidat": "Antoine Stéphane Roger",
      "expert1": {
        "name": "Graf Alexandre",
        "offres": {
          "_id": {
            "$oid": "66445f65d04cad996abc7c92"
          },
          "submit": []
        }
      },
      "expert2": {
        "name": "Gilloz Raphaël",
        "offres": {
          "_id": {
            "$oid": "66445f65d04cad996abc7c93"
          },
          "submit": []
        }
      },
      "boss": {
        "name": "Cyril Sokoloff",
        "offres": {
          "_id": {
            "$oid": "66445f65d04cad996abc7c94"
          },
          "submit": []
        }
      },
      "_id": {
        "$oid": "6631e6f58c7444839df0b096"
      }
    },
    {
      "refTpi": 1889,
      "id": "cfpv_2_2",
      "candidat": "Léonard Frauchiger",
      "expert1": {
        "name": "Pantic Nemanja",
        "offres": {
          "_id": {
            "$oid": "66445f65d04cad996abc7c96"
          },
          "submit": []
        }
      },
      "expert2": {
        "name": "Berney Daniel",
        "offres": {
          "_id": {
            "$oid": "66445f65d04cad996abc7c97"
          },
          "submit": []
        }
      },
      "boss": {
        "name": "Cyril Sokoloff",
        "offres": {
          "_id": {
            "$oid": "66445f65d04cad996abc7c98"
          },
          "submit": []
        }
      },
      "_id": {
        "$oid": "6631e6f48c7444839df0b078"
      }
    },
    {
      "refTpi": 1916,
      "id": "cfpv_2_3",
      "candidat": "Mohamed Salma Abdulkadir",
      "expert1": {
        "name": "Maillard Karim",
        "offres": {
          "_id": {
            "$oid": "66445f65d04cad996abc7c9a"
          },
          "submit": []
        }
      },
      "expert2": {
        "name": "Oberson Bernard",
        "offres": {
          "_id": {
            "$oid": "66445f65d04cad996abc7c9b"
          },
          "submit": []
        }
      },
      "boss": {
        "name": "Xavier Carrel",
        "offres": {
          "_id": {
            "$oid": "66445f65d04cad996abc7c9c"
          },
          "submit": []
        }
      },
      "_id": {
        "$oid": "6631e6f48c7444839df0b030"
      }
    },
    {
      "refTpi": 1934,
      "id": "cfpv_2_4",
      "candidat": "Samuel dos Santos",
      "expert1": {
        "name": "Oberson Bernard",
        "offres": {
          "_id": {
            "$oid": "66445f65d04cad996abc7c9e"
          },
          "submit": []
        }
      },
      "expert2": {
        "name": "Venries Luc",
        "offres": {
          "_id": {
            "$oid": "66445f65d04cad996abc7c9f"
          },
          "submit": []
        }
      },
      "boss": {
        "name": "Grégory Charmier",
        "offres": {
          "_id": {
            "$oid": "66445f65d04cad996abc7ca0"
          },
          "submit": []
        }
      },
      "_id": {
        "$oid": "6631e6f48c7444839df0b028"
      }
    },
    {
      "refTpi": 1925,
      "id": "cfpv_2_5",
      "candidat": "Matthe Suboonsan Chris Noah",
      "expert1": {
        "name": "Borboën Nicolas",
        "offres": {
          "_id": {
            "$oid": "66445f65d04cad996abc7ca2"
          },
          "submit": []
        }
      },
      "expert2": {
        "name": "Oberson Bernard",
        "offres": {
          "_id": {
            "$oid": "66445f65d04cad996abc7ca3"
          },
          "submit": []
        }
      },
      "boss": {
        "name": "Dimitrios Lymberis",
        "offres": {
          "_id": {
            "$oid": "66445f65d04cad996abc7ca4"
          },
          "submit": []
        }
      },
      "_id": {
        "$oid": "6631e6f48c7444839df0b074"
      }
    },
    {
      "refTpi": 1970,
      "id": "cfpv_2_6",
      "candidat": "Daddy Avdylaj Kevin",
      "expert1": {
        "name": "Borboën Nicolas",
        "offres": {
          "_id": {
            "$oid": "66445f65d04cad996abc7ca6"
          },
          "submit": []
        }
      },
      "expert2": {
        "name": "Benzonana Pascal",
        "offres": {
          "_id": {
            "$oid": "66445f65d04cad996abc7ca7"
          },
          "submit": []
        }
      },
      "boss": {
        "name": "Gael Sonney",
        "offres": {
          "_id": {
            "$oid": "66445f65d04cad996abc7ca8"
          },
          "submit": []
        }
      },
      "_id": {
        "$oid": "6631e6f48c7444839df0b052"
      }
    },
    {
      "refTpi": null,
      "id": "cfpv_2_7",
      "candidat": "",
      "expert1": {
        "name": "",
        "offres": {
          "_id": {
            "$oid": "66445f65d04cad996abc7caa"
          },
          "submit": []
        }
      },
      "expert2": {
        "name": "",
        "offres": {
          "_id": {
            "$oid": "66445f65d04cad996abc7cab"
          },
          "submit": []
        }
      },
      "boss": {
        "name": "",
        "offres": {
          "_id": {
            "$oid": "66445f65d04cad996abc7cac"
          },
          "submit": []
        }
      },
      "_id": {
        "$oid": "6631ea298c7444839df0b40b"
      }
    }
  ],
  "__v": 0
},
{
  "_id": {
    "$oid": "6631e6d98c7444839df0af5e"
  },
  "idRoom": 24129983,
  "lastUpdate": {
    "$numberLong": "1715756874176"
  },
  "site": "CFPV",
  "date": {
    "$date": "2024-06-12T00:00:00.000Z"
  },
  "name": "Vennes - A12",
  "configSite": {
    "breakline": 0.1667,
    "tpiTime": 1,
    "firstTpiStart": 8,
    "numSlots": 8
  },
  "tpiDatas": [
    {
      "refTpi": 1918,
      "id": "cfpv_3_0",
      "candidat": "Ella-Anelisse Corozel",
      "expert1": {
        "name": "Mellina Olivier",
        "offres": {
          "_id": {
            "$oid": "66445f65d04cad996abc7cb0"
          },
          "submit": []
        }
      },
      "expert2": {
        "name": "Ceran Süleyman",
        "offres": {
          "_id": {
            "$oid": "66445f65d04cad996abc7cb1"
          },
          "submit": []
        }
      },
      "boss": {
        "name": "Cédric Schaffter",
        "offres": {
          "_id": {
            "$oid": "66445f65d04cad996abc7cb2"
          },
          "submit": []
        }
      },
      "_id": {
        "$oid": "6631ea298c7444839df0b3f5"
      }
    },
    {
      "refTpi": 1919,
      "id": "cfpv_3_1",
      "candidat": "Marie Déglise Camille",
      "expert1": {
        "name": "Borboën Nicolas",
        "offres": {
          "_id": {
            "$oid": "66445f65d04cad996abc7cb4"
          },
          "submit": []
        }
      },
      "expert2": {
        "name": "Favre Raphaël",
        "offres": {
          "_id": {
            "$oid": "66445f65d04cad996abc7cb5"
          },
          "submit": []
        }
      },
      "boss": {
        "name": "Bertrand Sahli",
        "offres": {
          "_id": {
            "$oid": "66445f65d04cad996abc7cb6"
          },
          "submit": []
        }
      },
      "_id": {
        "$oid": "6631e6f48c7444839df0b04e"
      }
    },
    {
      "refTpi": 1881,
      "id": "cfpv_3_2",
      "candidat": "Fabrice Bred Geni Gelsomino",
      "expert1": {
        "name": "Ceran Süleyman",
        "offres": {
          "_id": {
            "$oid": "66445f65d04cad996abc7cb8"
          },
          "submit": []
        }
      },
      "expert2": {
        "name": "Bertino Yves",
        "offres": {
          "_id": {
            "$oid": "66445f65d04cad996abc7cb9"
          },
          "submit": []
        }
      },
      "boss": {
        "name": "Cédric Schaffter",
        "offres": {
          "_id": {
            "$oid": "66445f65d04cad996abc7cba"
          },
          "submit": []
        }
      },
      "_id": {
        "$oid": "6631e6f48c7444839df0b05a"
      }
    },
    {
      "refTpi": 1908,
      "id": "cfpv_3_3",
      "candidat": "Yann Mangiagli",
      "expert1": {
        "name": "Berney Daniel",
        "offres": {
          "_id": {
            "$oid": "66445f65d04cad996abc7cbc"
          },
          "submit": []
        }
      },
      "expert2": {
        "name": "Maret Gabriel",
        "offres": {
          "_id": {
            "$oid": "66445f65d04cad996abc7cbd"
          },
          "submit": []
        }
      },
      "boss": {
        "name": "Gael Sonney",
        "offres": {
          "_id": {
            "$oid": "66445f65d04cad996abc7cbe"
          },
          "submit": []
        }
      },
      "_id": {
        "$oid": "6631e6f48c7444839df0b02c"
      }
    },
    {
      "refTpi": 1890,
      "id": "cfpv_3_4",
      "candidat": "Leonar Dupuis",
      "expert1": {
        "name": "Borboën Nicolas",
        "offres": {
          "_id": {
            "$oid": "66445f65d04cad996abc7cc0"
          },
          "submit": []
        }
      },
      "expert2": {
        "name": "Ceran Süleyman",
        "offres": {
          "_id": {
            "$oid": "66445f65d04cad996abc7cc1"
          },
          "submit": []
        }
      },
      "boss": {
        "name": "Gael Sonney",
        "offres": {
          "_id": {
            "$oid": "66445f65d04cad996abc7cc2"
          },
          "submit": []
        }
      },
      "_id": {
        "$oid": "6631e6f48c7444839df0b084"
      }
    },
    {
      "refTpi": 1856,
      "id": "cfpv_3_5",
      "candidat": "Pruthvin Kandasamy",
      "expert1": {
        "name": "Mergim Krasniqi",
        "offres": {
          "_id": {
            "$oid": "66445f65d04cad996abc7cc4"
          },
          "submit": []
        }
      },
      "expert2": {
        "name": "Benzonana Pascal",
        "offres": {
          "_id": {
            "$oid": "66445f65d04cad996abc7cc5"
          },
          "submit": []
        }
      },
      "boss": {
        "name": "Mathieu Meylan",
        "offres": {
          "_id": {
            "$oid": "66445f65d04cad996abc7cc6"
          },
          "submit": []
        }
      },
      "_id": {
        "$oid": "6631e6f48c7444839df0b01c"
      }
    },
    {
      "refTpi": 1882,
      "id": "cfpv_3_6",
      "candidat": "Dylan Hentschel",
      "expert1": {
        "name": "Graf Alexandre",
        "offres": {
          "_id": {
            "$oid": "66445f65d04cad996abc7cc8"
          },
          "submit": []
        }
      },
      "expert2": {
        "name": "Gressly Matthieu",
        "offres": {
          "_id": {
            "$oid": "66445f65d04cad996abc7cc9"
          },
          "submit": []
        }
      },
      "boss": {
        "name": "Nicolas Cuendet",
        "offres": {
          "_id": {
            "$oid": "66445f65d04cad996abc7cca"
          },
          "submit": []
        }
      },
      "_id": {
        "$oid": "6631e6f58c7444839df0b092"
      }
    },
    {
      "refTpi": null,
      "id": "cfpv_3_7",
      "candidat": "",
      "expert1": {
        "name": "",
        "offres": {
          "_id": {
            "$oid": "66445f65d04cad996abc7ccc"
          },
          "submit": []
        }
      },
      "expert2": {
        "name": "",
        "offres": {
          "_id": {
            "$oid": "66445f65d04cad996abc7ccd"
          },
          "submit": []
        }
      },
      "boss": {
        "name": "",
        "offres": {
          "_id": {
            "$oid": "66445f65d04cad996abc7cce"
          },
          "submit": []
        }
      },
      "_id": {
        "$oid": "6631ea298c7444839df0b403"
      }
    }
  ],
  "__v": 0
},
{
  "_id": {
    "$oid": "6631e8b48c7444839df0b255"
  },
  "idRoom": 24130807,
  "lastUpdate": {
    "$numberLong": "1715756874176"
  },
  "site": "CFPV",
  "date": {
    "$date": "2024-06-12T00:00:00.000Z"
  },
  "name": "Vennes - A02",
  "configSite": {
    "breakline": 0.1667,
    "tpiTime": 1,
    "firstTpiStart": 8,
    "numSlots": 8
  },
  "tpiDatas": [
    {
      "refTpi": 1846,
      "id": "cfpv_4_0",
      "candidat": "Bustabad Yannick Pena",
      "expert1": {
        "name": "Graf Alexandre",
        "offres": {
          "_id": {
            "$oid": "66445f65d04cad996abc7cd2"
          },
          "submit": []
        }
      },
      "expert2": {
        "name": "Gonzalez Mikael",
        "offres": {
          "_id": {
            "$oid": "66445f65d04cad996abc7cd3"
          },
          "submit": []
        }
      },
      "boss": {
        "name": "Sheyla Oliveira Kobi",
        "offres": {
          "_id": {
            "$oid": "66445f65d04cad996abc7cd4"
          },
          "submit": []
        }
      },
      "_id": {
        "$oid": "6631ea298c7444839df0b3f3"
      }
    },
    {
      "refTpi": 1883,
      "id": "cfpv_4_1",
      "candidat": "Yann Imperadori",
      "expert1": {
        "name": "Oberson Bernard",
        "offres": {
          "_id": {
            "$oid": "66445f65d04cad996abc7cd6"
          },
          "submit": []
        }
      },
      "expert2": {
        "name": "Ceran Süleyman",
        "offres": {
          "_id": {
            "$oid": "66445f65d04cad996abc7cd7"
          },
          "submit": []
        }
      },
      "boss": {
        "name": "Cédric Schaffter",
        "offres": {
          "_id": {
            "$oid": "66445f65d04cad996abc7cd8"
          },
          "submit": []
        }
      },
      "_id": {
        "$oid": "6631e6f58c7444839df0b09e"
      }
    },
    {
      "refTpi": 1877,
      "id": "cfpv_4_2",
      "candidat": "Sean Kellen Ford",
      "expert1": {
        "name": "Oberson Bernard",
        "offres": {
          "_id": {
            "$oid": "66445f65d04cad996abc7cda"
          },
          "submit": []
        }
      },
      "expert2": {
        "name": "Maret Gabriel",
        "offres": {
          "_id": {
            "$oid": "66445f65d04cad996abc7cdb"
          },
          "submit": []
        }
      },
      "boss": {
        "name": "Isabelle Stucki",
        "offres": {
          "_id": {
            "$oid": "66445f65d04cad996abc7cdc"
          },
          "submit": []
        }
      },
      "_id": {
        "$oid": "6631e6f48c7444839df0b068"
      }
    },
    {
      "refTpi": 1854,
      "id": "cfpv_4_3",
      "candidat": "Simon Baeriswyl",
      "expert1": {
        "name": "Mellina Olivier",
        "offres": {
          "_id": {
            "$oid": "66445f65d04cad996abc7cde"
          },
          "submit": []
        }
      },
      "expert2": {
        "name": "Venries Luc",
        "offres": {
          "_id": {
            "$oid": "66445f65d04cad996abc7cdf"
          },
          "submit": []
        }
      },
      "boss": {
        "name": "Mathieu Meylan",
        "offres": {
          "_id": {
            "$oid": "66445f65d04cad996abc7ce0"
          },
          "submit": []
        }
      },
      "_id": {
        "$oid": "6631ea298c7444839df0b3f0"
      }
    },
    {
      "refTpi": 1874,
      "id": "cfpv_4_4",
      "candidat": "Bruno Grin",
      "expert1": {
        "name": "Mellina Olivier",
        "offres": {
          "_id": {
            "$oid": "66445f65d04cad996abc7ce2"
          },
          "submit": []
        }
      },
      "expert2": {
        "name": "Wolf Benjamin",
        "offres": {
          "_id": {
            "$oid": "66445f65d04cad996abc7ce3"
          },
          "submit": []
        }
      },
      "boss": {
        "name": "Mathieu Meylan",
        "offres": {
          "_id": {
            "$oid": "66445f65d04cad996abc7ce4"
          },
          "submit": []
        }
      },
      "_id": {
        "$oid": "6631e6f48c7444839df0b018"
      }
    },
    {
      "refTpi": 1954,
      "id": "cfpv_4_5",
      "candidat": "Ali Issolah",
      "expert1": {
        "name": "Wolf Benjamin",
        "offres": {
          "_id": {
            "$oid": "66445f65d04cad996abc7ce6"
          },
          "submit": []
        }
      },
      "expert2": {
        "name": "Maillard Karim",
        "offres": {
          "_id": {
            "$oid": "66445f65d04cad996abc7ce7"
          },
          "submit": []
        }
      },
      "boss": {
        "name": "Antoine Mveng",
        "offres": {
          "_id": {
            "$oid": "66445f65d04cad996abc7ce8"
          },
          "submit": []
        }
      },
      "_id": {
        "$oid": "6631e6f48c7444839df0b07c"
      }
    },
    {
      "refTpi": 1974,
      "id": "cfpv_4_6",
      "candidat": "Henry Chouriberry Noa",
      "expert1": {
        "name": "Wolf Benjamin",
        "offres": {
          "_id": {
            "$oid": "66445f65d04cad996abc7cea"
          },
          "submit": []
        }
      },
      "expert2": {
        "name": "Ceran Süleyman",
        "offres": {
          "_id": {
            "$oid": "66445f65d04cad996abc7ceb"
          },
          "submit": []
        }
      },
      "boss": {
        "name": "Antoine Mveng",
        "offres": {
          "_id": {
            "$oid": "66445f65d04cad996abc7cec"
          },
          "submit": []
        }
      },
      "_id": {
        "$oid": "6631e6f48c7444839df0b04a"
      }
    },
    {
      "refTpi": null,
      "id": "cfpv_4_7",
      "candidat": "",
      "expert1": {
        "name": "",
        "offres": {
          "_id": {
            "$oid": "66445f65d04cad996abc7cee"
          },
          "submit": []
        }
      },
      "expert2": {
        "name": "",
        "offres": {
          "_id": {
            "$oid": "66445f65d04cad996abc7cef"
          },
          "submit": []
        }
      },
      "boss": {
        "name": "",
        "offres": {
          "_id": {
            "$oid": "66445f65d04cad996abc7cf0"
          },
          "submit": []
        }
      },
      "_id": {
        "$oid": "6631ea298c7444839df0b407"
      }
    }
  ],
  "__v": 0
},
{
  "_id": {
    "$oid": "6631e6d98c7444839df0af81"
  },
  "idRoom": 24129999,
  "lastUpdate": {
    "$numberLong": "1715756874176"
  },
  "site": "CFPV",
  "date": {
    "$date": "2024-06-13T00:00:00.000Z"
  },
  "name": "Vennes - A11",
  "configSite": {
    "breakline": 0.1667,
    "tpiTime": 1,
    "firstTpiStart": 8,
    "numSlots": 8
  },
  "tpiDatas": [
    {
      "refTpi": 1917,
      "id": "cfpv_5_0",
      "candidat": "Fatima Ezzahra Abid",
      "expert1": {
        "name": "Montemayor Ernesto",
        "offres": {
          "_id": {
            "$oid": "66445f65d04cad996abc7cf4"
          },
          "submit": []
        }
      },
      "expert2": {
        "name": "Wolf Benjamin",
        "offres": {
          "_id": {
            "$oid": "66445f65d04cad996abc7cf5"
          },
          "submit": []
        }
      },
      "boss": {
        "name": "Xavier Carrel",
        "offres": {
          "_id": {
            "$oid": "66445f65d04cad996abc7cf6"
          },
          "submit": []
        }
      },
      "_id": {
        "$oid": "6631e6f48c7444839df0b014"
      }
    },
    {
      "refTpi": 1963,
      "id": "cfpv_5_1",
      "candidat": "Alexander Gaillard",
      "expert1": {
        "name": "Wolf Benjamin",
        "offres": {
          "_id": {
            "$oid": "66445f65d04cad996abc7cf8"
          },
          "submit": []
        }
      },
      "expert2": {
        "name": "Malherbe Roger",
        "offres": {
          "_id": {
            "$oid": "66445f65d04cad996abc7cf9"
          },
          "submit": []
        }
      },
      "boss": {
        "name": "Xavier Carrel",
        "offres": {
          "_id": {
            "$oid": "66445f65d04cad996abc7cfa"
          },
          "submit": []
        }
      },
      "_id": {
        "$oid": "6631e6f48c7444839df0b024"
      }
    },
    {
      "refTpi": 1942,
      "id": "cfpv_5_2",
      "candidat": "Saraneethan Shanthakumar",
      "expert1": {
        "name": "Roduit Jean-Luc",
        "offres": {
          "_id": {
            "$oid": "66445f65d04cad996abc7cfc"
          },
          "submit": []
        }
      },
      "expert2": {
        "name": "Wolf Benjamin",
        "offres": {
          "_id": {
            "$oid": "66445f65d04cad996abc7cfd"
          },
          "submit": []
        }
      },
      "boss": {
        "name": "Michel Delgado",
        "offres": {
          "_id": {
            "$oid": "66445f65d04cad996abc7cfe"
          },
          "submit": []
        }
      },
      "_id": {
        "$oid": "6631ea298c7444839df0b3f7"
      }
    },
    {
      "refTpi": 1880,
      "id": "cfpv_5_3",
      "candidat": "Sacha Jean Laurent Bourquard",
      "expert1": {
        "name": "Roduit Jean-Luc",
        "offres": {
          "_id": {
            "$oid": "66445f65d04cad996abc7d00"
          },
          "submit": []
        }
      },
      "expert2": {
        "name": "Wolf Benjamin",
        "offres": {
          "_id": {
            "$oid": "66445f65d04cad996abc7d01"
          },
          "submit": []
        }
      },
      "boss": {
        "name": "Nicolas Cuendet",
        "offres": {
          "_id": {
            "$oid": "66445f65d04cad996abc7d02"
          },
          "submit": []
        }
      },
      "_id": {
        "$oid": "6631e6f48c7444839df0b070"
      }
    },
    {
      "refTpi": 1870,
      "id": "cfpv_5_4",
      "candidat": "Dylan Bontems",
      "expert1": {
        "name": "Wolf Benjamin",
        "offres": {
          "_id": {
            "$oid": "66445f65d04cad996abc7d04"
          },
          "submit": []
        }
      },
      "expert2": {
        "name": "Malherbe Roger",
        "offres": {
          "_id": {
            "$oid": "66445f65d04cad996abc7d05"
          },
          "submit": []
        }
      },
      "boss": {
        "name": "Patrick Chenaux",
        "offres": {
          "_id": {
            "$oid": "66445f65d04cad996abc7d06"
          },
          "submit": []
        }
      },
      "_id": {
        "$oid": "6631e6f48c7444839df0b046"
      }
    },
    {
      "refTpi": 1872,
      "id": "cfpv_5_5",
      "candidat": "Alexandre Fernandes",
      "expert1": {
        "name": "Wolf Benjamin",
        "offres": {
          "_id": {
            "$oid": "66445f65d04cad996abc7d08"
          },
          "submit": []
        }
      },
      "expert2": {
        "name": "Malherbe Roger",
        "offres": {
          "_id": {
            "$oid": "66445f65d04cad996abc7d09"
          },
          "submit": []
        }
      },
      "boss": {
        "name": "Helder Manuel Costa Lopes",
        "offres": {
          "_id": {
            "$oid": "66445f65d04cad996abc7d0a"
          },
          "submit": []
        }
      },
      "_id": {
        "$oid": "6631e6f48c7444839df0b080"
      }
    },
    {
      "refTpi": 1973,
      "id": "cfpv_5_6",
      "candidat": "Thomas Rey",
      "expert1": {
        "name": "Wolf Benjamin",
        "offres": {
          "_id": {
            "$oid": "66445f65d04cad996abc7d0c"
          },
          "submit": []
        }
      },
      "expert2": {
        "name": "Viret Loic",
        "offres": {
          "_id": {
            "$oid": "66445f65d04cad996abc7d0d"
          },
          "submit": []
        }
      },
      "boss": {
        "name": "Dimitrios Lymberis",
        "offres": {
          "_id": {
            "$oid": "66445f65d04cad996abc7d0e"
          },
          "submit": []
        }
      },
      "_id": {
        "$oid": "6631e6f58c7444839df0b0ae"
      }
    },
    {
      "refTpi": null,
      "id": "cfpv_5_7",
      "candidat": "",
      "expert1": {
        "name": "",
        "offres": {
          "_id": {
            "$oid": "66445f65d04cad996abc7d10"
          },
          "submit": []
        }
      },
      "expert2": {
        "name": "",
        "offres": {
          "_id": {
            "$oid": "66445f65d04cad996abc7d11"
          },
          "submit": []
        }
      },
      "boss": {
        "name": "",
        "offres": {
          "_id": {
            "$oid": "66445f65d04cad996abc7d12"
          },
          "submit": []
        }
      },
      "_id": {
        "$oid": "6631ea298c7444839df0b40f"
      }
    }
  ],
  "__v": 0
},
{
  "_id": {
    "$oid": "6631e6d98c7444839df0afa4"
  },
  "idRoom": 24130014,
  "lastUpdate": {
    "$numberLong": "1715756874176"
  },
  "site": "CFPV",
  "date": {
    "$date": "2024-06-13T00:00:00.000Z"
  },
  "name": "Vennes - A12",
  "configSite": {
    "breakline": 0.1667,
    "tpiTime": 1,
    "firstTpiStart": 8,
    "numSlots": 8
  },
  "tpiDatas": [
    {
      "refTpi": 1875,
      "id": "cfpv_6_0",
      "candidat": "Timothee Victor Carlier",
      "expert1": {
        "name": "Graf Alexandre",
        "offres": {
          "_id": {
            "$oid": "66445f65d04cad996abc7d16"
          },
          "submit": []
        }
      },
      "expert2": {
        "name": "Sartoni Arnaud",
        "offres": {
          "_id": {
            "$oid": "66445f65d04cad996abc7d17"
          },
          "submit": []
        }
      },
      "boss": {
        "name": "Nicolas Cuendet",
        "offres": {
          "_id": {
            "$oid": "66445f65d04cad996abc7d18"
          },
          "submit": []
        }
      },
      "_id": {
        "$oid": "6631e6f48c7444839df0b06c"
      }
    },
    {
      "refTpi": 1886,
      "id": "cfpv_6_1",
      "candidat": "Jonathan Samuel Nicholas Dale",
      "expert1": {
        "name": "Roduit Jean-Luc",
        "offres": {
          "_id": {
            "$oid": "66445f65d04cad996abc7d1a"
          },
          "submit": []
        }
      },
      "expert2": {
        "name": "Pantic Nemanja",
        "offres": {
          "_id": {
            "$oid": "66445f65d04cad996abc7d1b"
          },
          "submit": []
        }
      },
      "boss": {
        "name": "Nicolas Cuendet",
        "offres": {
          "_id": {
            "$oid": "66445f65d04cad996abc7d1c"
          },
          "submit": []
        }
      },
      "_id": {
        "$oid": "6631e6f58c7444839df0b09a"
      }
    },
    {
      "refTpi": 1920,
      "id": "cfpv_6_2",
      "candidat": "Théo Ghaemmaghami",
      "expert1": {
        "name": "Wenger Serge",
        "offres": {
          "_id": {
            "$oid": "66445f65d04cad996abc7d1e"
          },
          "submit": []
        }
      },
      "expert2": {
        "name": "Berney Daniel",
        "offres": {
          "_id": {
            "$oid": "66445f65d04cad996abc7d1f"
          },
          "submit": []
        }
      },
      "boss": {
        "name": "Patrick Chenaux",
        "offres": {
          "_id": {
            "$oid": "66445f65d04cad996abc7d20"
          },
          "submit": []
        }
      },
      "_id": {
        "$oid": "6631e6f58c7444839df0b0a6"
      }
    },
    {
      "refTpi": 1956,
      "id": "cfpv_6_3",
      "candidat": "Kendy Song",
      "expert1": {
        "name": "Berney Daniel",
        "offres": {
          "_id": {
            "$oid": "66445f65d04cad996abc7d22"
          },
          "submit": []
        }
      },
      "expert2": {
        "name": "Andolfatto Frédérique",
        "offres": {
          "_id": {
            "$oid": "66445f65d04cad996abc7d23"
          },
          "submit": []
        }
      },
      "boss": {
        "name": "Jonathan Melly",
        "offres": {
          "_id": {
            "$oid": "66445f65d04cad996abc7d24"
          },
          "submit": []
        }
      },
      "_id": {
        "$oid": "6631ea298c7444839df0b3f1"
      }
    },
    {
      "refTpi": 1879,
      "id": "cfpv_6_4",
      "candidat": "Nicolas Berdoz",
      "expert1": {
        "name": "Pantic Nemanja",
        "offres": {
          "_id": {
            "$oid": "66445f65d04cad996abc7d26"
          },
          "submit": []
        }
      },
      "expert2": {
        "name": "Tonelli Jonathan",
        "offres": {
          "_id": {
            "$oid": "66445f65d04cad996abc7d27"
          },
          "submit": []
        }
      },
      "boss": {
        "name": "Laurent Duding",
        "offres": {
          "_id": {
            "$oid": "66445f65d04cad996abc7d28"
          },
          "submit": []
        }
      },
      "_id": {
        "$oid": "6631e6f48c7444839df0b03e"
      }
    },
    {
      "refTpi": 1855,
      "id": "cfpv_6_5",
      "candidat": "Diego Alfonso Da Silva",
      "expert1": {
        "name": "Roduit Jean-Luc",
        "offres": {
          "_id": {
            "$oid": "66445f65d04cad996abc7d2a"
          },
          "submit": []
        }
      },
      "expert2": {
        "name": "Tonelli Jonathan",
        "offres": {
          "_id": {
            "$oid": "66445f65d04cad996abc7d2b"
          },
          "submit": []
        }
      },
      "boss": {
        "name": "Laurent Duding",
        "offres": {
          "_id": {
            "$oid": "66445f65d04cad996abc7d2c"
          },
          "submit": []
        }
      },
      "_id": {
        "$oid": "6631e6f58c7444839df0b0a2"
      }
    },
    {
      "refTpi": 1940,
      "id": "cfpv_6_6",
      "candidat": "Kinan Jano",
      "expert1": {
        "name": "Berney Daniel",
        "offres": {
          "_id": {
            "$oid": "66445f65d04cad996abc7d2e"
          },
          "submit": []
        }
      },
      "expert2": {
        "name": "Malherbe Roger",
        "offres": {
          "_id": {
            "$oid": "66445f65d04cad996abc7d2f"
          },
          "submit": []
        }
      },
      "boss": {
        "name": "Helder Manuel Costa Lopes",
        "offres": {
          "_id": {
            "$oid": "66445f65d04cad996abc7d30"
          },
          "submit": []
        }
      },
      "_id": {
        "$oid": "6631e6f48c7444839df0b020"
      }
    },
    {
      "refTpi": null,
      "id": "cfpv_6_7",
      "candidat": "",
      "expert1": {
        "name": "",
        "offres": {
          "_id": {
            "$oid": "66445f65d04cad996abc7d32"
          },
          "submit": []
        }
      },
      "expert2": {
        "name": "",
        "offres": {
          "_id": {
            "$oid": "66445f65d04cad996abc7d33"
          },
          "submit": []
        }
      },
      "boss": {
        "name": "",
        "offres": {
          "_id": {
            "$oid": "66445f65d04cad996abc7d34"
          },
          "submit": []
        }
      },
      "_id": {
        "$oid": "6631ea298c7444839df0b413"
      }
    }
  ],
  "__v": 0
},
{
  "_id": {
    "$oid": "6631e8b48c7444839df0b278"
  },
  "idRoom": 24130849,
  "lastUpdate": {
    "$numberLong": "1715756874176"
  },
  "site": "CFPV",
  "date": {
    "$date": "2024-06-13T00:00:00.000Z"
  },
  "name": "Vennes - A02",
  "configSite": {
    "breakline": 0.1667,
    "tpiTime": 1,
    "firstTpiStart": 8,
    "numSlots": 8
  },
  "tpiDatas": [
    {
      "refTpi": 1949,
      "id": "cfpv_7_0",
      "candidat": "Salvatore Lombardo Robustiano",
      "expert1": {
        "name": "Malherbe Roger",
        "offres": {
          "_id": {
            "$oid": "66445f65d04cad996abc7d38"
          },
          "submit": []
        }
      },
      "expert2": {
        "name": "Berney Daniel",
        "offres": {
          "_id": {
            "$oid": "66445f65d04cad996abc7d39"
          },
          "submit": []
        }
      },
      "boss": {
        "name": "Karim Bourahla",
        "offres": {
          "_id": {
            "$oid": "66445f65d04cad996abc7d3a"
          },
          "submit": []
        }
      },
      "_id": {
        "$oid": "6631e6f48c7444839df0b056"
      }
    },
    {
      "refTpi": 1936,
      "id": "cfpv_7_1",
      "candidat": "Yu Wu Guo",
      "expert1": {
        "name": "Wenger Serge",
        "offres": {
          "_id": {
            "$oid": "66445f65d04cad996abc7d3c"
          },
          "submit": []
        }
      },
      "expert2": {
        "name": "Berney Daniel",
        "offres": {
          "_id": {
            "$oid": "66445f65d04cad996abc7d3d"
          },
          "submit": []
        }
      },
      "boss": {
        "name": "Patrick Chenaux",
        "offres": {
          "_id": {
            "$oid": "66445f65d04cad996abc7d3e"
          },
          "submit": []
        }
      },
      "_id": {
        "$oid": "6631ea298c7444839df0b3f4"
      }
    },
    {
      "refTpi": 1888,
      "id": "cfpv_7_2",
      "candidat": "Noah Favre",
      "expert1": {
        "name": "Montemayor Ernesto",
        "offres": {
          "_id": {
            "$oid": "66445f65d04cad996abc7d40"
          },
          "submit": []
        }
      },
      "expert2": {
        "name": "Tonelli Jonathan",
        "offres": {
          "_id": {
            "$oid": "66445f65d04cad996abc7d41"
          },
          "submit": []
        }
      },
      "boss": {
        "name": "Alain-Philippe Garraux",
        "offres": {
          "_id": {
            "$oid": "66445f65d04cad996abc7d42"
          },
          "submit": []
        }
      },
      "_id": {
        "$oid": "6631ea298c7444839df0b3f2"
      }
    },
    {
      "refTpi": 1876,
      "id": "cfpv_7_3",
      "candidat": "Lucie de Oliveira",
      "expert1": {
        "name": "Montemayor Ernesto",
        "offres": {
          "_id": {
            "$oid": "66445f65d04cad996abc7d44"
          },
          "submit": []
        }
      },
      "expert2": {
        "name": "Pretre Patrick",
        "offres": {
          "_id": {
            "$oid": "66445f65d04cad996abc7d45"
          },
          "submit": []
        }
      },
      "boss": {
        "name": "Alain-Philippe Garraux",
        "offres": {
          "_id": {
            "$oid": "66445f65d04cad996abc7d46"
          },
          "submit": []
        }
      },
      "_id": {
        "$oid": "6631e6f48c7444839df0b042"
      }
    },
    {
      "refTpi": 1923,
      "id": "cfpv_7_4",
      "candidat": "Bilal Mamo",
      "expert1": {
        "name": "Roduit Jean-Luc",
        "offres": {
          "_id": {
            "$oid": "66445f65d04cad996abc7d48"
          },
          "submit": []
        }
      },
      "expert2": {
        "name": "Berney Daniel",
        "offres": {
          "_id": {
            "$oid": "66445f65d04cad996abc7d49"
          },
          "submit": []
        }
      },
      "boss": {
        "name": "Karim Bourahla",
        "offres": {
          "_id": {
            "$oid": "66445f65d04cad996abc7d4a"
          },
          "submit": []
        }
      },
      "_id": {
        "$oid": "6631e6f58c7444839df0b0aa"
      }
    },
    {
      "refTpi": 1939,
      "id": "cfpv_7_5",
      "candidat": "Harun Findik",
      "expert1": {
        "name": "Wenger Serge",
        "offres": {
          "_id": {
            "$oid": "66445f65d04cad996abc7d4c"
          },
          "submit": []
        }
      },
      "expert2": {
        "name": "Andolfatto Frédérique",
        "offres": {
          "_id": {
            "$oid": "66445f65d04cad996abc7d4d"
          },
          "submit": []
        }
      },
      "boss": {
        "name": "Roberto Ferrari",
        "offres": {
          "_id": {
            "$oid": "66445f65d04cad996abc7d4e"
          },
          "submit": []
        }
      },
      "_id": {
        "$oid": "6631ea298c7444839df0b3f6"
      }
    },
    {
      "refTpi": null,
      "id": "cfpv_7_6",
      "candidat": "",
      "expert1": {
        "name": "",
        "offres": {
          "_id": {
            "$oid": "66445f65d04cad996abc7d50"
          },
          "submit": []
        }
      },
      "expert2": {
        "name": "",
        "offres": {
          "_id": {
            "$oid": "66445f65d04cad996abc7d51"
          },
          "submit": []
        }
      },
      "boss": {
        "name": "",
        "offres": {
          "_id": {
            "$oid": "66445f65d04cad996abc7d52"
          },
          "submit": []
        }
      },
      "_id": {
        "$oid": "6631ea298c7444839df0b417"
      }
    },
    {
      "refTpi": null,
      "id": "cfpv_7_7",
      "candidat": "",
      "expert1": {
        "name": "",
        "offres": {
          "_id": {
            "$oid": "66445f65d04cad996abc7d54"
          },
          "submit": []
        }
      },
      "expert2": {
        "name": "",
        "offres": {
          "_id": {
            "$oid": "66445f65d04cad996abc7d55"
          },
          "submit": []
        }
      },
      "boss": {
        "name": "",
        "offres": {
          "_id": {
            "$oid": "66445f65d04cad996abc7d56"
          },
          "submit": []
        }
      },
      "_id": {
        "$oid": "6631ea298c7444839df0b41b"
      }
    }
  ],
  "__v": 0
}]